{
    "title": "Plan studijske grupe",
    "class": "PlanStudijskeGrupe",
    "collumns": [
        "oznaka_ustanove",
        "oznaka_programa",
        "blok",
        "pozicija",
        "ustanova_predmet",
        "oznaka_predmeta"
    ],
    "key": [
        "oznaka_ustanove",
        "oznaka_programa",
        "blok",
        "pozicija"
    ],
    "attr_type": ["str", "str", "int", "int", "str", "str"],
    "attr_max": [2, 3, 2, 2, 2, 6],
    "linked_files": [],
    "path_to_file": "plan_studijske_grupe_data",
    "type": "serial",
    "db_table_name": "plan_studijske_grupe"
}